LICENSE
MANIFEST.in
README.md
setup.py
flake8_use_fstring/__init__.py
flake8_use_fstring/base.py
flake8_use_fstring/format.py
flake8_use_fstring/percent.py
flake8_use_fstring/prefix.py
flake8_use_fstring.egg-info/PKG-INFO
flake8_use_fstring.egg-info/SOURCES.txt
flake8_use_fstring.egg-info/dependency_links.txt
flake8_use_fstring.egg-info/entry_points.txt
flake8_use_fstring.egg-info/requires.txt
flake8_use_fstring.egg-info/top_level.txt